[
    {
        "nome": "Palazzo Chigi",
        "lat": 41.8991,
        "lon": 12.4808,
        "funzione": "Sede del Presidente del Consiglio",
        "accessibilita": "Accessibile",
        "note": "Ingresso da Piazza Colonna",
        "livello_allerta": 5,
        "distanza_da_palazzo_chigi_km": 0.0,
        "tempo_percorrenza_min": 0,
        "rischio_sismico": 3
    },
    {
        "nome": "Villa Doria Pamphilj",
        "lat": 41.8885,
        "lon": 12.4456,
        "funzione": "Residenza istituzionale",
        "accessibilita": "Limitata",
        "note": "Sede di incontri internazionali",
        "livello_allerta": 4,
        "distanza_da_palazzo_chigi_km": 3.15,
        "tempo_percorrenza_min": 13,
        "rischio_sismico": 2
    },
    {
        "nome": "Dipartimento della Protezione Civile",
        "lat": 41.9721,
        "lon": 12.4712,
        "funzione": "Coordinamento emergenze nazionali",
        "accessibilita": "Accessibile",
        "note": "Sede operativa in Via Vitorchiano",
        "livello_allerta": 5,
        "distanza_da_palazzo_chigi_km": 8.15,
        "tempo_percorrenza_min": 33,
        "rischio_sismico": 5
    },
    {
        "nome": "Dipartimento Funzione Pubblica",
        "lat": 41.9102,
        "lon": 12.4922,
        "funzione": "Gestione della PA",
        "accessibilita": "Accessibile",
        "note": "Ingresso da Via della Mercede",
        "livello_allerta": 3,
        "distanza_da_palazzo_chigi_km": 1.55,
        "tempo_percorrenza_min": 6,
        "rischio_sismico": 5
    },
    {
        "nome": "Palazzo Vidoni",
        "lat": 41.8975,
        "lon": 12.4789,
        "funzione": "Sede del Ministero della PA",
        "accessibilita": "Accessibile",
        "note": "Edificio storico",
        "livello_allerta": 3,
        "distanza_da_palazzo_chigi_km": 0.24,
        "tempo_percorrenza_min": 1,
        "rischio_sismico": 3
    },
    {
        "nome": "Palazzo Valentini",
        "lat": 41.8964,
        "lon": 12.4846,
        "funzione": "Sede della Città Metropolitana",
        "accessibilita": "Limitata",
        "note": "Presenza di vincoli architettonici",
        "livello_allerta": 2,
        "distanza_da_palazzo_chigi_km": 0.44,
        "tempo_percorrenza_min": 2,
        "rischio_sismico": 4
    },
    {
        "nome": "Palazzo Montecitorio",
        "lat": 41.9011,
        "lon": 12.4789,
        "funzione": "Camera dei Deputati",
        "accessibilita": "Accessibile",
        "note": "Sede parlamentare",
        "livello_allerta": 4,
        "distanza_da_palazzo_chigi_km": 0.27,
        "tempo_percorrenza_min": 1,
        "rischio_sismico": 6
    },
    {
        "nome": "Palazzo Madama",
        "lat": 41.8999,
        "lon": 12.4726,
        "funzione": "Senato della Repubblica",
        "accessibilita": "Accessibile",
        "note": "Sede parlamentare",
        "livello_allerta": 4,
        "distanza_da_palazzo_chigi_km": 0.69,
        "tempo_percorrenza_min": 3,
        "rischio_sismico": 5
    },
    {
        "nome": "Palazzo Spada",
        "lat": 41.8946,
        "lon": 12.4721,
        "funzione": "Consiglio di Stato",
        "accessibilita": "Limitata",
        "note": "Edificio storico",
        "livello_allerta": 2,
        "distanza_da_palazzo_chigi_km": 0.88,
        "tempo_percorrenza_min": 4,
        "rischio_sismico": 2
    },
    {
        "nome": "Scuola Nazionale dell'Amministrazione",
        "lat": 41.9355,
        "lon": 12.4638,
        "funzione": "Formazione dirigenti pubblici",
        "accessibilita": "Accessibile",
        "note": "Sede distaccata",
        "livello_allerta": 2,
        "distanza_da_palazzo_chigi_km": 7.67,
        "tempo_percorrenza_min": 30,
        "rischio_sismico": 7
    },
    {
        "nome": "Sede via della Mercede 9",
        "lat": 41.9033,
        "lon": 12.4823,
        "funzione": "Uffici",
        "accessibilita": "Alta",
        "livello_allerta": 2,
        "distanza_da_palazzo_chigi_km": 0.80,
        "tempo_percorrenza_min": 10,
        "note": "Dipartimento informazione e editoria",
        "rischio_sismico": 3
    },
    {
        "nome": "Sede via Sicilia 162",
        "lat": 41.9101,
        "lon": 12.4940,
        "funzione": "Uffici",
        "accessibilita": "Alta",
        "livello_allerta": 2,
        "distanza_da_palazzo_chigi_km": 4.45,
        "tempo_percorrenza_min": 22,
        "note": "Dipartimento per le politiche di coesione e per il sud",
        "rischio_sismico": 5
    }
]